LICENSE
MANIFEST.in
pyproject.toml
setup.cfg
setup.py
base/__init__.py
base/admin.py
base/apps.py
base/models.py
base/serializer.py
base/tests.py
base/urls.py
base/views.py
base/migrations/0001_initial.py
base/migrations/__init__.py
re_sannap_django_base.egg-info/PKG-INFO
re_sannap_django_base.egg-info/SOURCES.txt
re_sannap_django_base.egg-info/dependency_links.txt
re_sannap_django_base.egg-info/requires.txt
re_sannap_django_base.egg-info/top_level.txt